statici18n/__init__.py
statici18n/apps.py
statici18n/conf.py
statici18n/utils.py
statici18n/management/__init__.py
statici18n/management/commands/__init__.py
statici18n/management/commands/compilejsi18n.py
statici18n/templatetags/__init__.py
statici18n/templatetags/statici18n.py
django_statici18n-2.5.0.dist-info/LICENSE
django_statici18n-2.5.0.dist-info/METADATA
django_statici18n-2.5.0.dist-info/WHEEL
django_statici18n-2.5.0.dist-info/top_level.txt
django_statici18n-2.5.0.dist-info/RECORD
