Metadata-Version: 2.1
Name: django-statici18n
Version: 2.5.0
Summary: A Django app that compiles i18n JavaScript catalogs to static files.
Home-page: http://django-statici18n.readthedocs.org/
Author: Sebastien Fievet
Author-email: zyegfryed@gmail.com
License: BSD
Project-URL: Source, https://github.com/zyegfryed/django-statici18n
Classifier: Development Status :: 5 - Production/Stable
Classifier: Environment :: Web Environment
Classifier: Framework :: Django
Classifier: Intended Audience :: Developers
Classifier: License :: OSI Approved :: BSD License
Classifier: Operating System :: OS Independent
Classifier: Programming Language :: Python
Classifier: Programming Language :: Python :: 3
Classifier: Programming Language :: Python :: 3.6
Classifier: Programming Language :: Python :: 3.7
Classifier: Programming Language :: Python :: 3.8
Classifier: Programming Language :: Python :: 3.9
Classifier: Programming Language :: Python :: 3.10
Classifier: Programming Language :: Python :: 3.11
License-File: LICENSE
Requires-Dist: Django>=3.2
Requires-Dist: django-appconf>=1.0
